_layout.cp39-win_amd64.pyd
s_gd2/__init__.py
s_gd2/s_gd2.py
s_gd2/version.py
s_gd2/swig/__init__.py
s_gd2/swig/layout.py
s_gd2-1.8.1.dist-info/LICENSE
s_gd2-1.8.1.dist-info/METADATA
s_gd2-1.8.1.dist-info/WHEEL
s_gd2-1.8.1.dist-info/top_level.txt
s_gd2-1.8.1.dist-info/RECORD
