Metadata-Version: 2.1
Name: s-gd2
Version: 1.8.1
Summary: A package for performing stochastic gradient descent (arXiv:1710.04626) to layout graphs
Home-page: https://www.github.com/jxz12/s_gd2
Author: Jonathan Zheng
Author-email: jxz12@ic.ac.uk
License-File: LICENSE
Requires-Dist: numpy (>=1.16)
Provides-Extra: test
Requires-Dist: nose2 ; extra == 'test'
